{
  "130": {
    "baslik": "BEIN SPORTS 1 (ZIRVE)",
    "url": "https://five.4928d54d950ee70q25.lat/yayinzirve.m3u8|referer=https://trgoals1369.xyz/",
    "logo": "https://example.com/logo/1.png",
    "grup": "ÜmitVIP~Spor"
  },
  "131": {
    "baslik": "BEIN SPORTS 1 (1)",
    "url": "https://five.4928d54d950ee70q25.lat/yayin1.m3u8|referer=https://trgoals1369.xyz/",
    "logo": "https://example.com/logo/2.png",
    "grup": "ÜmitVIP~Spor"
  },
  "132": {
    "baslik": "BEIN SPORTS 1 (INAT)",
    "url": "https://five.4928d54d950ee70q25.lat/yayininat.m3u8|referer=https://trgoals1369.xyz/",
    "logo": "https://example.com/logo/3.png",
    "grup": "ÜmitVIP~Spor"
  },
  "133": {
    "baslik": "BEIN SPORTS 2",
    "url": "https://five.4928d54d950ee70q25.lat/yayinb2.m3u8|referer=https://trgoals1369.xyz/",
    "logo": "https://example.com/logo/4.png",
    "grup": "ÜmitVIP~Spor"
  },
  "134": {
    "baslik": "BEIN SPORTS 3",
    "url": "https://five.4928d54d950ee70q25.lat/yayinb3.m3u8|referer=https://trgoals1369.xyz/",
    "logo": "https://example.com/logo/5.png",
    "grup": "ÜmitVIP~Spor"
  },
  "135": {
    "baslik": "BEIN SPORTS 4",
    "url": "https://five.4928d54d950ee70q25.lat/yayinb4.m3u8|referer=https://trgoals1369.xyz/",
    "logo": "https://example.com/logo/6.png",
    "grup": "ÜmitVIP~Spor"
  },
  "136": {
    "baslik": "BEIN SPORTS 5",
    "url": "https://five.4928d54d950ee70q25.lat/yayinb5.m3u8|referer=https://trgoals1369.xyz/",
    "logo": "https://example.com/logo/7.png",
    "grup": "ÜmitVIP~Spor"
  },
  "137": {
    "baslik": "BEIN SPORTS MAX 1",
    "url": "https://five.4928d54d950ee70q25.lat/yayinbm1.m3u8|referer=https://trgoals1369.xyz/",
    "logo": "https://example.com/logo/8.png",
    "grup": "ÜmitVIP~Spor"
  },
  "138": {
    "baslik": "BEIN SPORTS MAX 2",
    "url": "https://five.4928d54d950ee70q25.lat/yayinbm2.m3u8|referer=https://trgoals1369.xyz/",
    "logo": "https://example.com/logo/9.png",
    "grup": "ÜmitVIP~Spor"
  },
  "139": {
    "baslik": "S SPORT 1",
    "url": "https://five.4928d54d950ee70q25.lat/yayinss.m3u8|referer=https://trgoals1369.xyz/",
    "logo": "https://example.com/logo/10.png",
    "grup": "ÜmitVIP~Spor"
  },
  "140": {
    "baslik": "S SPORT 2",
    "url": "https://five.4928d54d950ee70q25.lat/yayinss2.m3u8|referer=https://trgoals1369.xyz/",
    "logo": "https://example.com/logo/11.png",
    "grup": "ÜmitVIP~Spor"
  },
  "141": {
    "baslik": "TIVIBU SPOR 1",
    "url": "https://five.4928d54d950ee70q25.lat/yayint1.m3u8|referer=https://trgoals1369.xyz/",
    "logo": "https://example.com/logo/13.png",
    "grup": "ÜmitVIP~Spor"
  },
  "142": {
    "baslik": "TIVIBU SPOR 2",
    "url": "https://five.4928d54d950ee70q25.lat/yayint2.m3u8|referer=https://trgoals1369.xyz/",
    "logo": "https://example.com/logo/14.png",
    "grup": "ÜmitVIP~Spor"
  },
  "143": {
    "baslik": "TIVIBU SPOR 3",
    "url": "https://five.4928d54d950ee70q25.lat/yayint3.m3u8|referer=https://trgoals1369.xyz/",
    "logo": "https://example.com/logo/15.png",
    "grup": "ÜmitVIP~Spor"
  },
  "144": {
    "baslik": "SPOR SMART 1",
    "url": "https://five.4928d54d950ee70q25.lat/yayinsmarts.m3u8|referer=https://trgoals1369.xyz/",
    "logo": "https://example.com/logo/16.png",
    "grup": "ÜmitVIP~Spor"
  },
  "145": {
    "baslik": "SPOR SMART 2",
    "url": "https://five.4928d54d950ee70q25.lat/yayinsms2.m3u8|referer=https://trgoals1369.xyz/",
    "logo": "https://example.com/logo/17.png",
    "grup": "ÜmitVIP~Spor"
  },
  "146": {
    "baslik": "TRT SPOR 1",
    "url": "https://five.4928d54d950ee70q25.lat/yayintrtspor.m3u8|referer=https://trgoals1369.xyz/",
    "logo": "https://example.com/logo/18.png",
    "grup": "ÜmitVIP~Spor"
  },
  "147": {
    "baslik": "TRT SPOR 2",
    "url": "https://five.4928d54d950ee70q25.lat/yayintrtspor2.m3u8|referer=https://trgoals1369.xyz/",
    "logo": "https://example.com/logo/19.png",
    "grup": "ÜmitVIP~Spor"
  },
  "148": {
    "baslik": "TRT 1",
    "url": "https://five.4928d54d950ee70q25.lat/yayintrt1.m3u8|referer=https://trgoals1369.xyz/",
    "logo": "https://example.com/logo/20.png",
    "grup": "ÜmitVIP~Spor"
  },
  "149": {
    "baslik": "A SPOR",
    "url": "https://five.4928d54d950ee70q25.lat/yayinas.m3u8|referer=https://trgoals1369.xyz/",
    "logo": "https://example.com/logo/21.png",
    "grup": "ÜmitVIP~Spor"
  },
  "150": {
    "baslik": "ATV",
    "url": "https://five.4928d54d950ee70q25.lat/yayinatv.m3u8|referer=https://trgoals1369.xyz/",
    "logo": "https://example.com/logo/22.png",
    "grup": "ÜmitVIP~Spor"
  },
  "151": {
    "baslik": "TV 8",
    "url": "https://five.4928d54d950ee70q25.lat/yayintv8.m3u8|referer=https://trgoals1369.xyz/",
    "logo": "https://example.com/logo/23.png",
    "grup": "ÜmitVIP~Spor"
  },
  "152": {
    "baslik": "TV 8.5",
    "url": "https://five.4928d54d950ee70q25.lat/yayintv85.m3u8|referer=https://trgoals1369.xyz/",
    "logo": "https://example.com/logo/24.png",
    "grup": "ÜmitVIP~Spor"
  },
  "153": {
    "baslik": "FORMULA 1",
    "url": "https://five.4928d54d950ee70q25.lat/yayinf1.m3u8|referer=https://trgoals1369.xyz/",
    "logo": "https://example.com/logo/25.png",
    "grup": "ÜmitVIP~Spor"
  },
  "154": {
    "baslik": "NBA TV",
    "url": "https://five.4928d54d950ee70q25.lat/yayinnbatv.m3u8|referer=https://trgoals1369.xyz/",
    "logo": "https://example.com/logo/26.png",
    "grup": "ÜmitVIP~Spor"
  },
  "155": {
    "baslik": "EURO SPORT 1",
    "url": "https://five.4928d54d950ee70q25.lat/yayineu1.m3u8|referer=https://trgoals1369.xyz/",
    "logo": "https://example.com/logo/27.png",
    "grup": "ÜmitVIP~Spor"
  },
  "156": {
    "baslik": "EURO SPORT 2",
    "url": "https://five.4928d54d950ee70q25.lat/yayineu2.m3u8|referer=https://trgoals1369.xyz/",
    "logo": "https://example.com/logo/28.png",
    "grup": "ÜmitVIP~Spor"
  },
  "157": {
    "baslik": "S SPORT PLUS 2",
    "url": "https://five.4928d54d950ee70q25.lat/yayinex1.m3u8|referer=https://trgoals1369.xyz/",
    "logo": "https://example.com/logo/29.png",
    "grup": "ÜmitVIP~Spor"
  },
  "158": {
    "baslik": "S SPORT PLUS 1",
    "url": "https://five.4928d54d950ee70q25.lat/yayinex2.m3u8|referer=https://trgoals1369.xyz/",
    "logo": "https://example.com/logo/30.png",
    "grup": "ÜmitVIP~Spor"
  },
  "159": {
    "baslik": "EXXEN SPOR 3",
    "url": "https://five.4928d54d950ee70q25.lat/yayinex3.m3u8|referer=https://trgoals1369.xyz/",
    "logo": "https://example.com/logo/31.png",
    "grup": "ÜmitVIP~Spor"
  },
  "160": {
    "baslik": "EXXEN SPOR 4",
    "url": "https://five.4928d54d950ee70q25.lat/yayinex4.m3u8|referer=https://trgoals1369.xyz/",
    "logo": "https://example.com/logo/32.png",
    "grup": "ÜmitVIP~Spor"
  },
  "161": {
    "baslik": "EXXEN SPOR 5",
    "url": "https://five.4928d54d950ee70q25.lat/yayinex5.m3u8|referer=https://trgoals1369.xyz/",
    "logo": "https://example.com/logo/33.png",
    "grup": "ÜmitVIP~Spor"
  },
  "162": {
    "baslik": "EXXEN SPOR 6",
    "url": "https://five.4928d54d950ee70q25.lat/yayinex6.m3u8|referer=https://trgoals1369.xyz/",
    "logo": "https://example.com/logo/34.png",
    "grup": "ÜmitVIP~Spor"
  },
  "163": {
    "baslik": "EXXEN SPOR 7",
    "url": "https://five.4928d54d950ee70q25.lat/yayinex7.m3u8|referer=https://trgoals1369.xyz/",
    "logo": "https://example.com/logo/35.png",
    "grup": "ÜmitVIP~Spor"
  },
  "164": {
    "baslik": "EXXEN SPOR 8",
    "url": "https://five.4928d54d950ee70q25.lat/yayinex8.m3u8|referer=https://trgoals1369.xyz/",
    "logo": "https://example.com/logo/36.png",
    "grup": "ÜmitVIP~Spor"
  }
}